arx/__init__.py
pyarx-0.1.2.dist-info/WHEEL
pyarx-0.1.2.dist-info/METADATA
pyarx-0.1.2.dist-info/RECORD
