Metadata-Version: 2.1
Name: pyarx
Version: 0.1.2
Summary: Stor
Author: karansthr
Author-email: karansthr97@gmail.com
Requires-Python: >=3.8,<4.0
Classifier: Programming Language :: Python :: 3
Classifier: Programming Language :: Python :: 3.8
Classifier: Programming Language :: Python :: 3.9
Requires-Dist: requests (>=2.26.0,<3.0.0)
